MANIFEST.in
setup.py
RMControl.egg-info/PKG-INFO
RMControl.egg-info/SOURCES.txt
RMControl.egg-info/dependency_links.txt
RMControl.egg-info/requires.txt
RMControl.egg-info/top_level.txt
rmcontrol/__init__.py
rmcontrol/database/rmcontrol.db
rmcontrol/database/schema.sql
rmcontrol/static/app.css
rmcontrol/static/app.js
rmcontrol/templates/index.html