Metadata-Version: 1.0
Name: RMControl
Version: 1.0.1
Summary: A python app to control an RM2 from BroadLink.
Home-page: https://github.com/ericmagnuson/rmcontrol
Author: Eric Magnuson
Author-email: eric@ericmagnuson.me
License: LICENSE.txt
Platform: UNKNOWN
